pycoxmunk/CM_Calcs.py
pycoxmunk/CM_Constants.py
pycoxmunk/CM_Main.py
pycoxmunk/CM_PixMask.py
pycoxmunk/CM_SceneGeom.py
pycoxmunk/CM_Shared_Wind.py
pycoxmunk/CM_Utils.py
pycoxmunk/__init__.py
pycoxmunk/Tests/__init__.py
pycoxmunk/Tests/test_CMCalcs.py
pycoxmunk/Tests/test_CM_main.py
pycoxmunk/Tests/test_PixMask.py
pycoxmunk/Tests/test_SceneGeom.py
pycoxmunk/Tests/test_SharedWind.py
pycoxmunk/Tests/test_Utils.py
pycoxmunk/Tests/test_WaterConsts.py
pycoxmunk-1.1.0.dist-info/LICENSE
pycoxmunk-1.1.0.dist-info/METADATA
pycoxmunk-1.1.0.dist-info/WHEEL
pycoxmunk-1.1.0.dist-info/top_level.txt
pycoxmunk-1.1.0.dist-info/RECORD
