Metadata-Version: 2.1
Name: pycoxmunk
Version: 1.1.0
Summary: An algorithm to compute sea surface reflectance using the Cox-Munk approach.
Home-page: https://github.com/simonrp84/PyCoxMunk
Author: Simon R Proud
Author-email: Simon R Proud <simon.proud@stfc.ac.uk>
License: GPLv3
Project-URL: Homepage, https://github.com/simonrp84/PyCoxMunk
Keywords: satellite,oceanography,remote-sensing,earth-observation,reflectance
Classifier: License :: OSI Approved :: GNU General Public License v3 (GPLv3)
Classifier: Programming Language :: Python
Classifier: Programming Language :: Python :: 3
Requires-Python: >=3.8
License-File: LICENSE
Requires-Dist: numpy (>=1.21.2)
Requires-Dist: scipy (>=1.7.1)
Requires-Dist: pandas (>=1.3.4)
Requires-Dist: dask (>=2021.10.0)
Requires-Dist: pyorbital (>=1.7.1)
Requires-Dist: pyresample (>=1.22.1)
Requires-Dist: satpy (>=0.30)
Requires-Dist: click (>=8.0.3)
Requires-Dist: numba (>=0.55.0)
Requires-Dist: xarray (>=0.20.2)
